{
  "opening": {
    "id": "r1b1kbnr/pp3ppp/1qn1p3/3pP3/2pP4/P1P2N2/1P3PPP/RNBQKB1R w KQkq - 0 7",
    "name": "French: Advance, 5.Nf3 Qb6 6.a3 c4",
    "eco": "C02",
    "aliases": "\"[]\""
  },
  "videos": [
    {
      "id": "OBdwqgQ9pLo",
      "title": "French Defense - Advanced Variation lesson by Vladimir Fedoseev (Aeroflot Open 2018.)",
      "channel": "Hanging Pawns",
      "duration": 522,
      "views": 2058,
      "published": "2018-02-24T08:48:45Z",
      "thumbnail": "https://i.ytimg.com/vi/OBdwqgQ9pLo/default.jpg",
      "url": "https://youtube.com/watch?v=OBdwqgQ9pLo",
      "score": 100
    },
    {
      "id": "plgs6rbCMjE",
      "title": "Advance Variation of the French Defense (C02) ⎸Chess Openings",
      "channel": "Hanging Pawns",
      "duration": 1375,
      "views": 138763,
      "published": "2018-05-25T11:15:19Z",
      "thumbnail": "https://i.ytimg.com/vi/plgs6rbCMjE/default.jpg",
      "url": "https://youtube.com/watch?v=plgs6rbCMjE",
      "score": 90
    },
    {
      "id": "pig559oP5OM",
      "title": "Introduction to the French Defense ⎸Chess Openings",
      "channel": "Hanging Pawns",
      "duration": 1269,
      "views": 259783,
      "published": "2018-04-28T16:13:24Z",
      "thumbnail": "https://i.ytimg.com/vi/pig559oP5OM/default.jpg",
      "url": "https://youtube.com/watch?v=pig559oP5OM",
      "score": 90
    },
    {
      "id": "UhnB8mA94qQ",
      "title": "French Defense Game: The Critical Moments | Viewers' Choice - GM Elshan Moradiabadi",
      "channel": "Saint Louis Chess Club",
      "duration": 2378,
      "views": 37665,
      "published": "2017-05-08T17:00:01Z",
      "thumbnail": "https://i.ytimg.com/vi/UhnB8mA94qQ/default.jpg",
      "url": "https://youtube.com/watch?v=UhnB8mA94qQ",
      "score": 75
    },
    {
      "id": "lEKwdDwnE90",
      "title": "Pawn Structure #2: French Defence | Strategy Session with Jonathan Schrantz",
      "channel": "Saint Louis Chess Club",
      "duration": 1487,
      "views": 76230,
      "published": "2016-10-06T17:00:02Z",
      "thumbnail": "https://i.ytimg.com/vi/lEKwdDwnE90/default.jpg",
      "url": "https://youtube.com/watch?v=lEKwdDwnE90",
      "score": 75
    }
  ],
  "metadata": {
    "total_videos": 5,
    "generated_at": "2025-07-20T02:37:13.615Z",
    "cache_version": "6359ad9d"
  }
}