{
  "opening": {
    "id": "r1bq1rk1/pp2bppp/4p3/3n4/1n1P4/2NB1N2/PP3PPP/R1BQR1K1 w - - 5 11",
    "name": "QGD: Semi-Tarrasch, 7.Bd3 Main Line, 10.Re1 Ncb4",
    "eco": "D42",
    "aliases": "\"[]\""
  },
  "videos": [
    {
      "id": "KNg5A_XZGfY",
      "title": "Semi-Tarrasch Defense Opening Theory",
      "channel": "Hanging Pawns",
      "duration": 1353,
      "views": 28216,
      "published": "2020-02-06T17:11:03Z",
      "thumbnail": "https://i.ytimg.com/vi/KNg5A_XZGfY/default.jpg",
      "url": "https://youtube.com/watch?v=KNg5A_XZGfY",
      "score": 115
    }
  ],
  "metadata": {
    "total_videos": 1,
    "generated_at": "2025-07-20T02:37:16.448Z",
    "cache_version": "446227b8"
  }
}