{
  "opening": {
    "id": "r1bqkb1r/pppp1ppp/2n2n2/4N3/4P3/8/PPPP1PPP/RNBQKB1R w KQkq - 1 4",
    "name": "Petrov's Defense: Stafford Gambit",
    "eco": "C42",
    "aliases": "\"{\\\"ct\\\":\\\"Russian Game, Stafford Gambit\\\",\\\"chessGraph\\\":\\\"Stafford Gambit, Petroff\\\",\\\"icsbot\\\":\\\"Stafford Gambit, Petroff \\\"}\""
  },
  "videos": [
    {
      "id": "XkB4IVNaZWw",
      "title": "A Beginner Lesson in the Stafford Gambit",
      "channel": "Eric Rosen",
      "duration": 3449,
      "views": 2547858,
      "published": "2021-04-14T10:00:15Z",
      "thumbnail": "https://i.ytimg.com/vi/XkB4IVNaZWw/default.jpg",
      "url": "https://youtube.com/watch?v=XkB4IVNaZWw",
      "score": 145
    },
    {
      "id": "FkFYkrAwNjw",
      "title": "How to Beat the Stafford Gambit | Speedrun Episode 14",
      "channel": "Eric Rosen",
      "duration": 1079,
      "views": 126177,
      "published": "2023-12-23T16:45:00Z",
      "thumbnail": "https://i.ytimg.com/vi/FkFYkrAwNjw/default.jpg",
      "url": "https://youtube.com/watch?v=FkFYkrAwNjw",
      "score": 140
    },
    {
      "id": "zsc7rDteis4",
      "title": "How to CRUSH the Stafford Gambit (and other chess opening secrets)",
      "channel": "Eric Rosen",
      "duration": 4429,
      "views": 83816,
      "published": "2021-10-12T22:30:10Z",
      "thumbnail": "https://i.ytimg.com/vi/zsc7rDteis4/default.jpg",
      "url": "https://youtube.com/watch?v=zsc7rDteis4",
      "score": 130
    },
    {
      "id": "XVVGpVTGSnI",
      "title": "12 Difficult Chess Openings, and How to Beat Them! | The Dynamic Dozen",
      "channel": "Saint Louis Chess Club",
      "duration": 2976,
      "views": 94801,
      "published": "2021-02-12T18:00:10Z",
      "thumbnail": "https://i.ytimg.com/vi/XVVGpVTGSnI/default.jpg",
      "url": "https://youtube.com/watch?v=XVVGpVTGSnI",
      "score": 125
    },
    {
      "id": "2zTK0dFcx70",
      "title": "Discovering Dubious (but venomous) Opening Theory",
      "channel": "Eric Rosen",
      "duration": 1204,
      "views": 138386,
      "published": "2020-08-08T12:00:01Z",
      "thumbnail": "https://i.ytimg.com/vi/2zTK0dFcx70/default.jpg",
      "url": "https://youtube.com/watch?v=2zTK0dFcx70",
      "score": 125
    },
    {
      "id": "jMTWY6ra9Kw",
      "title": "Enjoy the Stafford Gambit? Try this opening!",
      "channel": "Eric Rosen",
      "duration": 823,
      "views": 380859,
      "published": "2020-08-18T10:30:03Z",
      "thumbnail": "https://i.ytimg.com/vi/jMTWY6ra9Kw/default.jpg",
      "url": "https://youtube.com/watch?v=jMTWY6ra9Kw",
      "score": 115
    },
    {
      "id": "16Q6Po-s6Gs",
      "title": "Beating Everyone with the Same Opening Trap (Stafford Gambit)",
      "channel": "Eric Rosen",
      "duration": 660,
      "views": 6108982,
      "published": "2020-08-01T12:15:00Z",
      "thumbnail": "https://i.ytimg.com/vi/16Q6Po-s6Gs/default.jpg",
      "url": "https://youtube.com/watch?v=16Q6Po-s6Gs",
      "score": 115
    },
    {
      "id": "D2Rlg3oVPZU",
      "title": "Opening Traps, Gambits, & Rare Ideas MASTERCLASS | ft. Grandmaster Aman Hambleton",
      "channel": "Eric Rosen",
      "duration": 9531,
      "views": 340961,
      "published": "2020-12-04T13:00:03Z",
      "thumbnail": "https://i.ytimg.com/vi/D2Rlg3oVPZU/default.jpg",
      "url": "https://youtube.com/watch?v=D2Rlg3oVPZU",
      "score": 110
    },
    {
      "id": "8urm2D1HhX8",
      "title": "Master Class | Stafford Gambit / BongCloud!!! | Chess Speedrun | Grandmaster Naroditsky",
      "channel": "Daniel Naroditsky",
      "duration": 2550,
      "views": 162543,
      "published": "2021-08-25T04:28:36Z",
      "thumbnail": "https://i.ytimg.com/vi/8urm2D1HhX8/default.jpg",
      "url": "https://youtube.com/watch?v=8urm2D1HhX8",
      "score": 105
    },
    {
      "id": "lLzLAJcRn-Q",
      "title": "Snuffing the Stafford Gambit | Busting the Gambits with GM Naro",
      "channel": "Daniel Naroditsky",
      "duration": 1675,
      "views": 218733,
      "published": "2020-09-07T00:14:45Z",
      "thumbnail": "https://i.ytimg.com/vi/lLzLAJcRn-Q/default.jpg",
      "url": "https://youtube.com/watch?v=lLzLAJcRn-Q",
      "score": 105
    }
  ],
  "metadata": {
    "total_videos": 10,
    "generated_at": "2025-07-20T02:37:14.473Z",
    "cache_version": "8d3c05fe"
  }
}