{
  "opening": {
    "id": "r3k1r1/ppqbnp2/2n1p3/3pP3/5P2/P1pQ4/2P1N1PP/R1B1KB1R w KQq - 0 13",
    "name": "French: Winawer, Poisoned Pawn, Main Line",
    "eco": "C18",
    "aliases": "\"[]\""
  },
  "videos": [
    {
      "id": "PuI4MWpDe2U",
      "title": "Steinitz Variation of the Classical French (C11) ⎸Chess Openings",
      "channel": "Hanging Pawns",
      "duration": 1593,
      "views": 52100,
      "published": "2018-05-14T12:18:30Z",
      "thumbnail": "https://i.ytimg.com/vi/PuI4MWpDe2U/default.jpg",
      "url": "https://youtube.com/watch?v=PuI4MWpDe2U",
      "score": 90
    },
    {
      "id": "NWFL6b38BUQ",
      "title": "Winawer Variation of the French Defense (C15-C19) ⎸Chess Openings",
      "channel": "Hanging Pawns",
      "duration": 1382,
      "views": 76302,
      "published": "2018-05-02T12:14:30Z",
      "thumbnail": "https://i.ytimg.com/vi/NWFL6b38BUQ/default.jpg",
      "url": "https://youtube.com/watch?v=NWFL6b38BUQ",
      "score": 90
    }
  ],
  "metadata": {
    "total_videos": 2,
    "generated_at": "2025-07-20T02:37:14.008Z",
    "cache_version": "21c8027b"
  }
}