{
  "opening": {
    "id": "rnbqkbnr/pp2pppp/8/2p5/3PpB2/8/PPP2PPP/RN1QKBNR w KQkq - 0 4",
    "name": "Queen's Pawn Game: Accelerated London System, Steinitz Countergambit, Morris Countergambit Accepted",
    "eco": "D00",
    "aliases": "\"{\\\"chessGraph\\\":\\\"Morris Counter-Gambit\\\",\\\"icsbot\\\":\\\"Morris Counter-Gambit \\\"}\""
  },
  "videos": [
    {
      "id": "kv2zFGYMDEc",
      "title": "Be prepared for the Morris Countergambit! · Training Game",
      "channel": "Hanging Pawns",
      "duration": 3036,
      "views": 5581,
      "published": "2023-12-06T13:00:39Z",
      "thumbnail": "https://i.ytimg.com/vi/kv2zFGYMDEc/default.jpg",
      "url": "https://youtube.com/watch?v=kv2zFGYMDEc",
      "score": 85
    },
    {
      "id": "_0q9KmNCnzY",
      "title": "A forced advantage against the London System? · Training Game",
      "channel": "Hanging Pawns",
      "duration": 2449,
      "views": 6332,
      "published": "2023-12-10T13:00:23Z",
      "thumbnail": "https://i.ytimg.com/vi/_0q9KmNCnzY/default.jpg",
      "url": "https://youtube.com/watch?v=_0q9KmNCnzY",
      "score": 75
    },
    {
      "id": "KVBlmQTHKqY",
      "title": "Don't like the London System? Don't allow it! Here's how. · Training Game",
      "channel": "Hanging Pawns",
      "duration": 2616,
      "views": 14676,
      "published": "2023-11-30T13:00:25Z",
      "thumbnail": "https://i.ytimg.com/vi/KVBlmQTHKqY/default.jpg",
      "url": "https://youtube.com/watch?v=KVBlmQTHKqY",
      "score": 75
    },
    {
      "id": "X8mK2G61azA",
      "title": "Here's why many hate facing the London System · Training Game",
      "channel": "Hanging Pawns",
      "duration": 2762,
      "views": 7326,
      "published": "2023-11-27T13:00:23Z",
      "thumbnail": "https://i.ytimg.com/vi/X8mK2G61azA/default.jpg",
      "url": "https://youtube.com/watch?v=X8mK2G61azA",
      "score": 75
    },
    {
      "id": "NcMfRYiIDis",
      "title": "Here's the problem with the London System · Training Game",
      "channel": "Hanging Pawns",
      "duration": 3254,
      "views": 8481,
      "published": "2023-11-16T13:00:18Z",
      "thumbnail": "https://i.ytimg.com/vi/NcMfRYiIDis/default.jpg",
      "url": "https://youtube.com/watch?v=NcMfRYiIDis",
      "score": 75
    },
    {
      "id": "0EuifNxXkcs",
      "title": "The textbook London System mating attack · Training Game",
      "channel": "Hanging Pawns",
      "duration": 3314,
      "views": 6285,
      "published": "2023-11-03T13:00:01Z",
      "thumbnail": "https://i.ytimg.com/vi/0EuifNxXkcs/default.jpg",
      "url": "https://youtube.com/watch?v=0EuifNxXkcs",
      "score": 75
    },
    {
      "id": "Az_Llgj8k9A",
      "title": "Punishing black's most common blunder in the London System · Training Game",
      "channel": "Hanging Pawns",
      "duration": 631,
      "views": 7694,
      "published": "2023-11-18T13:00:12Z",
      "thumbnail": "https://i.ytimg.com/vi/Az_Llgj8k9A/default.jpg",
      "url": "https://youtube.com/watch?v=Az_Llgj8k9A",
      "score": 70
    }
  ],
  "metadata": {
    "total_videos": 7,
    "generated_at": "2025-07-20T02:37:15.756Z",
    "cache_version": "97a0520e"
  }
}