{
  "opening": {
    "id": "rnbqkb1r/pppppnpp/5p2/8/3PP3/5N2/PPP2PPP/RNBQKB1R w KQkq - 1 4",
    "name": "Zukertort Opening: Arctic Defense, Drunken Knight Variation",
    "eco": "A04",
    "aliases": "\"{\\\"ct\\\":\\\"Zukertort Opening, Arctic Defense\\\"}\""
  },
  "videos": [
    {
      "id": "a2aTwmu-N4g",
      "title": "I Can't Stop Playing GAMBITS",
      "channel": "Eric Rosen",
      "duration": 3383,
      "views": 91561,
      "published": "2022-10-02T18:00:01Z",
      "thumbnail": "https://i.ytimg.com/vi/a2aTwmu-N4g/default.jpg",
      "url": "https://youtube.com/watch?v=a2aTwmu-N4g",
      "score": 85
    }
  ],
  "metadata": {
    "total_videos": 1,
    "generated_at": "2025-07-20T02:37:10.040Z",
    "cache_version": "9991ddf0"
  }
}