{
  "opening": {
    "id": "rnbqkbnr/pp2pppp/8/2pp4/3P4/5N2/PPP1PPPP/RNBQKB1R w KQkq - 0 3",
    "name": "Queen's Pawn Game: Krause Variation",
    "eco": "D02",
    "aliases": "\"{\\\"scid\\\":\\\"Queen's Pawn: Krause Variation\\\",\\\"ct\\\":\\\"Zukertort Opening, Reversed Queen's Gambit\\\",\\\"chessGraph\\\":\\\"Queen's Gambit Reversed; Krause Variation\\\",\\\"icsbot\\\":\\\"Queen's Gambit Reversed; Krause Variation \\\"}\""
  },
  "videos": [
    {
      "id": "NiZZbGG4QtI",
      "title": "Double Attack: Making the Most of a Move | Tactics Time!",
      "channel": "Saint Louis Chess Club",
      "duration": 1460,
      "views": 8533,
      "published": "2017-03-02T18:06:35Z",
      "thumbnail": "https://i.ytimg.com/vi/NiZZbGG4QtI/default.jpg",
      "url": "https://youtube.com/watch?v=NiZZbGG4QtI",
      "score": 85
    },
    {
      "id": "a2aTwmu-N4g",
      "title": "I Can't Stop Playing GAMBITS",
      "channel": "Eric Rosen",
      "duration": 3383,
      "views": 91561,
      "published": "2022-10-02T18:00:01Z",
      "thumbnail": "https://i.ytimg.com/vi/a2aTwmu-N4g/default.jpg",
      "url": "https://youtube.com/watch?v=a2aTwmu-N4g",
      "score": 85
    },
    {
      "id": "t9aBal-Hzxk",
      "title": "Akiba Rubinstein offers Oldrich Duras a queen | Vienna 1908",
      "channel": "ChessNetwork",
      "duration": 1035,
      "views": 113176,
      "published": "2018-06-05T02:58:25Z",
      "thumbnail": "https://i.ytimg.com/vi/t9aBal-Hzxk/default.jpg",
      "url": "https://youtube.com/watch?v=t9aBal-Hzxk",
      "score": 80
    }
  ],
  "metadata": {
    "total_videos": 3,
    "generated_at": "2025-07-20T02:37:15.792Z",
    "cache_version": "8b86755c"
  }
}