{
  "opening": {
    "id": "rnbqkbnr/pppppppp/8/8/8/7N/PPPPPPPP/RNBQKB1R b KQkq - 1 1",
    "name": "Amar Opening",
    "eco": "A00",
    "aliases": "\"{\\\"scid\\\":\\\"Amar/Paris Opening\\\",\\\"eco_wikip\\\":\\\"Irregular Openings: Amar Opening\\\",\\\"ct\\\":\\\"Amar Opening, General\\\",\\\"chessGraph\\\":\\\"Amar; Paris Opening\\\",\\\"chronos\\\":\\\"Amar (Paris) opening\\\",\\\"icsbot\\\":\\\"Amar; Paris Opening \\\"}\""
  },
  "videos": [],
  "metadata": {
    "total_videos": 0,
    "generated_at": "2025-07-20T02:37:09.808Z",
    "cache_version": "88188704"
  }
}