{
  "opening": {
    "id": "rnbqkb1r/4pppp/p1p2n2/1p1p4/2PP4/1PN1PN2/P4PPP/R1BQKB1R b KQkq - 0 6",
    "name": "Slav: Chameleon, 5.e3 b5 6.b3",
    "eco": "D15",
    "aliases": "\"[]\""
  },
  "videos": [
    {
      "id": "c1_wWyUBOOw",
      "title": "Slav Defense Theory: Chameleon Variation",
      "channel": "Hanging Pawns",
      "duration": 1664,
      "views": 37810,
      "published": "2019-11-03T12:38:48Z",
      "thumbnail": "https://i.ytimg.com/vi/c1_wWyUBOOw/default.jpg",
      "url": "https://youtube.com/watch?v=c1_wWyUBOOw",
      "score": 115
    }
  ],
  "metadata": {
    "total_videos": 1,
    "generated_at": "2025-07-20T02:37:16.003Z",
    "cache_version": "0f7592a2"
  }
}