{
  "opening": {
    "id": "rnbqk2r/ppp1ppbp/3p1np1/8/2BPPP2/2N5/PPP3PP/R1BQK1NR b KQkq - 2 5",
    "name": "Pirc Defense: Austrian Attack, Ljubojevic Variation",
    "eco": "B09",
    "aliases": "\"{\\\"scid\\\":\\\"Pirc: Austrian, Ljubojevic Variation\\\",\\\"ct\\\":\\\"Pirc Defense, Austrian Attack\\\",\\\"chessGraph\\\":\\\"Ljubojevic Variation, Pirc\\\",\\\"chronos\\\":\\\"Pirc: Austrian attack, Ljubojevic variation\\\",\\\"icsbot\\\":\\\"Ljubojevic Variation, Pirc \\\"}\""
  },
  "videos": [
    {
      "id": "MURLEtPvCvY",
      "title": "Sveshnikov and Kholmov Systems | Pirc Defense Opening Theory",
      "channel": "Hanging Pawns",
      "duration": 1300,
      "views": 17777,
      "published": "2019-02-28T16:48:21Z",
      "thumbnail": "https://i.ytimg.com/vi/MURLEtPvCvY/default.jpg",
      "url": "https://youtube.com/watch?v=MURLEtPvCvY",
      "score": 145
    },
    {
      "id": "WUgtRXm6DtY",
      "title": "Byrne Variation | Pirc Defense Opening Theory",
      "channel": "Hanging Pawns",
      "duration": 1399,
      "views": 21594,
      "published": "2019-02-26T18:02:17Z",
      "thumbnail": "https://i.ytimg.com/vi/WUgtRXm6DtY/default.jpg",
      "url": "https://youtube.com/watch?v=WUgtRXm6DtY",
      "score": 145
    },
    {
      "id": "7W2dB74VcUQ",
      "title": "The Austrian Attack | Pirc Defense Opening Theory",
      "channel": "Hanging Pawns",
      "duration": 1360,
      "views": 97563,
      "published": "2019-02-19T16:02:12Z",
      "thumbnail": "https://i.ytimg.com/vi/7W2dB74VcUQ/default.jpg",
      "url": "https://youtube.com/watch?v=7W2dB74VcUQ",
      "score": 145
    },
    {
      "id": "TIpUDMzQVmU",
      "title": "TRAP THE QUEEN!! | Deep Dive - Pirc Defense: Classical | GM Naroditsky’s Top Theory Speedrun",
      "channel": "Daniel Naroditsky",
      "duration": 3573,
      "views": 170676,
      "published": "2023-01-08T04:15:52Z",
      "thumbnail": "https://i.ytimg.com/vi/TIpUDMzQVmU/default.jpg",
      "url": "https://youtube.com/watch?v=TIpUDMzQVmU",
      "score": 145
    },
    {
      "id": "rHOZ65s-IlY",
      "title": "150 Attack | Pirc Defense Opening Theory",
      "channel": "Hanging Pawns",
      "duration": 1096,
      "views": 51438,
      "published": "2019-02-24T16:46:17Z",
      "thumbnail": "https://i.ytimg.com/vi/rHOZ65s-IlY/default.jpg",
      "url": "https://youtube.com/watch?v=rHOZ65s-IlY",
      "score": 140
    },
    {
      "id": "YeVjKcTT8Gs",
      "title": "A Complete 1.e4 Opening Repertoire for White",
      "channel": "Hanging Pawns",
      "duration": 2851,
      "views": 20372,
      "published": "2025-03-24T11:33:40Z",
      "thumbnail": "https://i.ytimg.com/vi/YeVjKcTT8Gs/default.jpg",
      "url": "https://youtube.com/watch?v=YeVjKcTT8Gs",
      "score": 125
    },
    {
      "id": "Je1dRnNV6IQ",
      "title": "Four Pawns Attack | King’s Indian Defense Theory",
      "channel": "Hanging Pawns",
      "duration": 1775,
      "views": 38790,
      "published": "2019-06-19T17:47:53Z",
      "thumbnail": "https://i.ytimg.com/vi/Je1dRnNV6IQ/default.jpg",
      "url": "https://youtube.com/watch?v=Je1dRnNV6IQ",
      "score": 125
    },
    {
      "id": "2vJoqXVTXjM",
      "title": "Standard Line and Tiger’s Modern | Modern Defense Opening Theory",
      "channel": "Hanging Pawns",
      "duration": 1447,
      "views": 61187,
      "published": "2019-03-12T18:50:35Z",
      "thumbnail": "https://i.ytimg.com/vi/2vJoqXVTXjM/default.jpg",
      "url": "https://youtube.com/watch?v=2vJoqXVTXjM",
      "score": 125
    },
    {
      "id": "EJmjt9GGhA8",
      "title": "Opening Ideas: Pirc Defense - GM Yasser Seirawan - 2013.06.05",
      "channel": "Saint Louis Chess Club",
      "duration": 3492,
      "views": 477644,
      "published": "2013-06-20T20:27:32Z",
      "thumbnail": "https://i.ytimg.com/vi/EJmjt9GGhA8/default.jpg",
      "url": "https://youtube.com/watch?v=EJmjt9GGhA8",
      "score": 120
    },
    {
      "id": "l8kuosZc9Dk",
      "title": "The Three Pawns Attack | Modern Defense Opening Theory",
      "channel": "Hanging Pawns",
      "duration": 901,
      "views": 40870,
      "published": "2019-03-05T13:42:26Z",
      "thumbnail": "https://i.ytimg.com/vi/l8kuosZc9Dk/default.jpg",
      "url": "https://youtube.com/watch?v=l8kuosZc9Dk",
      "score": 120
    }
  ],
  "metadata": {
    "total_videos": 10,
    "generated_at": "2025-07-20T02:37:12.021Z",
    "cache_version": "8b5f34fd"
  }
}