{
  "opening": {
    "id": "rnbqk2r/pppp1ppp/5n2/2b1p3/2B1P3/2N5/PPPP1PPP/R1BQK1NR w KQkq - 4 4",
    "name": "Vienna: 3.Bc4 Bc5",
    "eco": "C26",
    "aliases": "\"{\\\"chessGraph\\\":\\\"Bishop Variation, Vienna\\\",\\\"icsbot\\\":\\\"Bishop Variation, Vienna \\\"}\""
  },
  "videos": [
    {
      "id": "6QQ5sw-SgNw",
      "title": "The Vienna Game | Chess Openings Explained",
      "channel": "Saint Louis Chess Club",
      "duration": 2826,
      "views": 657584,
      "published": "2021-02-09T01:33:46Z",
      "thumbnail": "https://i.ytimg.com/vi/6QQ5sw-SgNw/default.jpg",
      "url": "https://youtube.com/watch?v=6QQ5sw-SgNw",
      "score": 145
    },
    {
      "id": "4jGu9nx_Xro",
      "title": "The Max Lange Defense · Vienna Game Theory",
      "channel": "Hanging Pawns",
      "duration": 1882,
      "views": 20899,
      "published": "2024-02-06T08:54:08Z",
      "thumbnail": "https://i.ytimg.com/vi/4jGu9nx_Xro/default.jpg",
      "url": "https://youtube.com/watch?v=4jGu9nx_Xro",
      "score": 145
    },
    {
      "id": "YeVjKcTT8Gs",
      "title": "A Complete 1.e4 Opening Repertoire for White",
      "channel": "Hanging Pawns",
      "duration": 2851,
      "views": 20372,
      "published": "2025-03-24T11:33:40Z",
      "thumbnail": "https://i.ytimg.com/vi/YeVjKcTT8Gs/default.jpg",
      "url": "https://youtube.com/watch?v=YeVjKcTT8Gs",
      "score": 125
    },
    {
      "id": "fqQHlOCFmW8",
      "title": "Nimzowitsch Defense Opening Theory",
      "channel": "Hanging Pawns",
      "duration": 2308,
      "views": 65496,
      "published": "2019-05-29T13:21:41Z",
      "thumbnail": "https://i.ytimg.com/vi/fqQHlOCFmW8/default.jpg",
      "url": "https://youtube.com/watch?v=fqQHlOCFmW8",
      "score": 125
    },
    {
      "id": "FV67KSxkJQw",
      "title": "The Vienna Game: Ideas, Principles and Common Variations · Chess Openings",
      "channel": "Hanging Pawns",
      "duration": 1254,
      "views": 70185,
      "published": "2024-01-19T12:45:32Z",
      "thumbnail": "https://i.ytimg.com/vi/FV67KSxkJQw/default.jpg",
      "url": "https://youtube.com/watch?v=FV67KSxkJQw",
      "score": 120
    },
    {
      "id": "ZNpske8zAoo",
      "title": "How to Use the Vienna Opening to TRICK and DESTROY your Opponents! | SlowBrah Ep.5",
      "channel": "chessbrah",
      "duration": 965,
      "views": 41514,
      "published": "2023-07-17T15:15:04Z",
      "thumbnail": "https://i.ytimg.com/vi/ZNpske8zAoo/default.jpg",
      "url": "https://youtube.com/watch?v=ZNpske8zAoo",
      "score": 115
    },
    {
      "id": "Et-7l2PcCI8",
      "title": "Netflix's The Queen's Gambit: Episodes 1-2 | Chess Openings Explained - NM Caleb Denby",
      "channel": "Saint Louis Chess Club",
      "duration": 4030,
      "views": 15204,
      "published": "2021-01-12T01:41:37Z",
      "thumbnail": "https://i.ytimg.com/vi/Et-7l2PcCI8/default.jpg",
      "url": "https://youtube.com/watch?v=Et-7l2PcCI8",
      "score": 110
    },
    {
      "id": "CprohVlhSSA",
      "title": "Romantic Openings: Then and Now | Chess Openings Explained - NM Caleb Denby",
      "channel": "Saint Louis Chess Club",
      "duration": 3890,
      "views": 10223,
      "published": "2020-12-29T01:41:02Z",
      "thumbnail": "https://i.ytimg.com/vi/CprohVlhSSA/default.jpg",
      "url": "https://youtube.com/watch?v=CprohVlhSSA",
      "score": 110
    },
    {
      "id": "eStsxnEzvI4",
      "title": "Réti Opening: Ideas, Principles, Theory, Transpositions, Structures · Chess Openings",
      "channel": "Hanging Pawns",
      "duration": 4442,
      "views": 15152,
      "published": "2025-01-25T08:49:07Z",
      "thumbnail": "https://i.ytimg.com/vi/eStsxnEzvI4/default.jpg",
      "url": "https://youtube.com/watch?v=eStsxnEzvI4",
      "score": 110
    },
    {
      "id": "NKeSyWouCPc",
      "title": "The Vienna Gambit · Ideas, Patterns, Traps and all Variations",
      "channel": "Hanging Pawns",
      "duration": 1826,
      "views": 29275,
      "published": "2024-02-02T15:00:07Z",
      "thumbnail": "https://i.ytimg.com/vi/NKeSyWouCPc/default.jpg",
      "url": "https://youtube.com/watch?v=NKeSyWouCPc",
      "score": 105
    }
  ],
  "metadata": {
    "total_videos": 10,
    "generated_at": "2025-07-20T02:37:14.134Z",
    "cache_version": "350a9f41"
  }
}